hexutil/__init__.py
hexutil-0.2.2.dist-info/DESCRIPTION.rst
hexutil-0.2.2.dist-info/METADATA
hexutil-0.2.2.dist-info/RECORD
hexutil-0.2.2.dist-info/WHEEL
hexutil-0.2.2.dist-info/metadata.json
hexutil-0.2.2.dist-info/top_level.txt
